shadowd/__init__.py
shadowd/cgi_connector.py
shadowd/connector.py
shadowd/django_connector.py
shadowd/flask_connector.py
shadowd/werkzeug_connector.py
shadowd-3.0.2.dist-info/LICENSE
shadowd-3.0.2.dist-info/METADATA
shadowd-3.0.2.dist-info/WHEEL
shadowd-3.0.2.dist-info/top_level.txt
shadowd-3.0.2.dist-info/RECORD
