Metadata-Version: 2.1
Name: shadowd
Version: 3.0.2
Summary: Python connector for the Shadow Daemon web application firewall
Home-page: http://github.com/zecure/shadowd_python
Author: Hendrik Buchwald
Author-email: hb@zecure.org
License: GPLv2
Keywords: waf security shadowd
Platform: UNKNOWN
Classifier: Development Status :: 5 - Production/Stable
Classifier: Intended Audience :: System Administrators
Classifier: Environment :: Web Environment
Classifier: License :: OSI Approved :: GNU General Public License v2 (GPLv2)
Classifier: Programming Language :: Python :: 2
Classifier: Topic :: Internet :: WWW/HTTP
Classifier: Topic :: System :: Networking :: Firewalls
